bamboosnow/__init__.py
bamboosnow/client.py
bamboosnow/errors.py
bamboosnow/http.py
bamboosnow/py.typed
bamboosnow/types.py
bamboosnow/resources/__init__.py
bamboosnow/resources/agents.py
bamboosnow/resources/api_keys.py
bamboosnow/resources/repositories.py
bamboosnow/resources/runs.py
bamboosnow/resources/users.py
bamboosnow-0.1.0.dist-info/METADATA
bamboosnow-0.1.0.dist-info/WHEEL
bamboosnow-0.1.0.dist-info/RECORD
