Metadata-Version: 2.4
Name: bamboosnow
Version: 0.1.0
Summary: Official Python SDK for BambooSnow AI agent automation platform
Project-URL: Homepage, https://bamboosnow.co
Project-URL: Documentation, https://bamboosnow.co/docs/sdk/python
Project-URL: Repository, https://github.com/bamboosnow/bamboosnow
Project-URL: Issues, https://github.com/bamboosnow/bamboosnow/issues
Author-email: BambooSnow <support@bamboosnow.co>
License-Expression: MIT
Keywords: agent,ai,api,automation,bamboosnow,sdk
Classifier: Development Status :: 4 - Beta
Classifier: Intended Audience :: Developers
Classifier: License :: OSI Approved :: MIT License
Classifier: Programming Language :: Python :: 3
Classifier: Programming Language :: Python :: 3.9
Classifier: Programming Language :: Python :: 3.10
Classifier: Programming Language :: Python :: 3.11
Classifier: Programming Language :: Python :: 3.12
Classifier: Typing :: Typed
Requires-Python: >=3.9
Requires-Dist: httpx>=0.25.0
Requires-Dist: pydantic>=2.0.0
Provides-Extra: dev
Requires-Dist: mypy>=1.9.0; extra == 'dev'
Requires-Dist: pytest-asyncio>=0.23.0; extra == 'dev'
Requires-Dist: pytest-httpx>=0.30.0; extra == 'dev'
Requires-Dist: pytest>=8.0.0; extra == 'dev'
Requires-Dist: ruff>=0.4.0; extra == 'dev'
